ProjectAliceSK/ProjectAliceSkillKit.py
ProjectAliceSK/__init__.py
ProjectAliceSK/pyproject.toml
ProjectAliceSK/create/__init__.py
ProjectAliceSK/create/create.py
ProjectAliceSK/create/templates/.editorconfig
ProjectAliceSK/create/templates/.gitignore.j2
ProjectAliceSK/create/templates/.gitlab-ci.yml.j2
ProjectAliceSK/create/templates/LICENSE.j2
ProjectAliceSK/create/templates/README.md.j2
ProjectAliceSK/create/templates/dialog.json.j2
ProjectAliceSK/create/templates/mypy.ini
ProjectAliceSK/create/templates/mypy_requirements.txt
ProjectAliceSK/create/templates/sample.json.j2
ProjectAliceSK/create/templates/skill.py.j2
ProjectAliceSK/create/templates/sonar-project.properties.j2
ProjectAliceSK/create/templates/talks.json.j2
ProjectAliceSK/create/templates/tests.yml.j2
ProjectAliceSK/create/templates/devices/device.config.template.j2
ProjectAliceSK/create/templates/devices/device.py.j2
ProjectAliceSK/create/templates/nodes/locales.json.j2
ProjectAliceSK/create/templates/nodes/node.html.j2
ProjectAliceSK/create/templates/nodes/node.js.j2
ProjectAliceSK/create/templates/nodes/package.json.j2
ProjectAliceSK/create/templates/widgets/widget.css.j2
ProjectAliceSK/create/templates/widgets/widget.html.j2
ProjectAliceSK/create/templates/widgets/widget.js.j2
ProjectAliceSK/create/templates/widgets/widget.py.j2
ProjectAliceSK/makeTalks/TalkCreator.py
ProjectAliceSK/makeTalks/__init__.py
ProjectAliceSK/makeTalks/makeTalks.py
ProjectAliceSK/unittests/__init__.py
ProjectAliceSK/unittests/unittests.py
ProjectAliceSK/util/Helpers.py
ProjectAliceSK/util/__init__.py
ProjectAliceSK/validate/JsonValidator.py
ProjectAliceSK/validate/__init__.py
ProjectAliceSK/validate/src/ConfigValidation.py
ProjectAliceSK/validate/src/DialogTemplate.py
ProjectAliceSK/validate/src/DialogValidation.py
ProjectAliceSK/validate/src/InstallValidation.py
ProjectAliceSK/validate/src/SamplesValidation.py
ProjectAliceSK/validate/src/TalkValidation.py
ProjectAliceSK/validate/src/Validation.py
projectalice_sk-2.3.4.dist-info/LICENSE
projectalice_sk-2.3.4.dist-info/METADATA
projectalice_sk-2.3.4.dist-info/WHEEL
projectalice_sk-2.3.4.dist-info/entry_points.txt
projectalice_sk-2.3.4.dist-info/top_level.txt
projectalice_sk-2.3.4.dist-info/RECORD
