Metadata-Version: 2.1
Name: projectalice-sk
Version: 2.3.4
Summary: Project Alice skill kit
Home-page: https://github.com/project-alice-assistant/ProjectAliceSkillKit
Author: ProjectAlice
Maintainer: Psychokiller1888
Maintainer-email: laurentchervet@bluewin.ch
License: GPL-3.0
Classifier: Development Status :: 5 - Production/Stable
Classifier: Environment :: Console
Classifier: Intended Audience :: Developers
Classifier: License :: OSI Approved :: GNU General Public License v3 (GPLv3)
Classifier: Operating System :: OS Independent
Classifier: Programming Language :: Python :: 3.7
Classifier: Topic :: Software Development :: Code Generators
Classifier: Topic :: Software Development :: Testing
License-File: LICENSE
Requires-Dist: AliceGit
Requires-Dist: jsonschema (>=3.0.0)
Requires-Dist: click
Requires-Dist: unidecode
Requires-Dist: requests
Requires-Dist: InquirerPy (~=0.3.1)
Requires-Dist: jinja2
Requires-Dist: pytest (~=6.2.5)
Requires-Dist: coverage (~=6.2)
Requires-Dist: pytest-cov (~=3.0.0)
Requires-Dist: coveralls (~=3.3.1)
Requires-Dist: types-requests
